.gitignore
.travis.yml
MANIFEST.in
README.md
README.pypi
logs.log
requirements.txt
screenshot.png
setup.py
test.md
.travis/install_orange.sh
Orange3_Finecon.egg-info/PKG-INFO
Orange3_Finecon.egg-info/SOURCES.txt
Orange3_Finecon.egg-info/dependency_links.txt
Orange3_Finecon.egg-info/entry_points.txt
Orange3_Finecon.egg-info/namespace_packages.txt
Orange3_Finecon.egg-info/not-zip-safe
Orange3_Finecon.egg-info/requires.txt
Orange3_Finecon.egg-info/top_level.txt
doc/Makefile
doc/conf.py
doc/index.rst
doc/make.bat
orangecontrib/__init__.py
orangecontrib/FinEcon/tutorials/example_tutorial.ows
orangecontrib/FinEcon/widgets/icons/.DS_Store
orangecontrib/FinEcon/widgets/icons/A股交易数据.svg
orangecontrib/FinEcon/widgets/icons/Pandas.svg
orangecontrib/FinEcon/widgets/icons/R.svg
orangecontrib/FinEcon/widgets/icons/category.svg
orangecontrib/FinEcon/widgets/icons/finecon.svg
orangecontrib/FinEcon/widgets/icons/julia.svg
orangecontrib/FinEcon/widgets/icons/misc.svg
orangecontrib/FinEcon/widgets/icons/mywidget.svg
orangecontrib/FinEcon/widgets/icons/pandas2.svg
orangecontrib/FinEcon/widgets/icons/stata.svg
orangecontrib/FinEcon/widgets/icons/中国宏观.svg
orangecontrib/FinEcon/widgets/icons/市场指数.svg
orangecontrib/FinEcon/widgets/icons/框框.svg
orangecontrib/FinEcon/widgets/icons/美国宏观.svg
orangecontrib/FinEcon/widgets/icons/财务数据.svg
orangecontrib/finecon/__init__.py
orangecontrib/finecon/tests/__init__.py
orangecontrib/finecon/tests/test_example.py
orangecontrib/finecon/tutorials/__init__.py
orangecontrib/finecon/tutorials/example_tutorial.ows
orangecontrib/finecon/widgets/__init__.py
orangecontrib/finecon/widgets/owabnormret.py
orangecontrib/finecon/widgets/owakshare.py
orangecontrib/finecon/widgets/owbatchimport.py
orangecontrib/finecon/widgets/owfinanceidx.py
orangecontrib/finecon/widgets/owjbfile.py
orangecontrib/finecon/widgets/owmacrocn.py
orangecontrib/finecon/widgets/owmacrousa.py
orangecontrib/finecon/widgets/owmarkitindex.py
orangecontrib/finecon/widgets/pandasScript.py
orangecontrib/finecon/widgets/pyR.py
orangecontrib/finecon/widgets/pyjulia.py
orangecontrib/finecon/widgets/icons/A股交易数据.svg
orangecontrib/finecon/widgets/icons/Pandas.svg
orangecontrib/finecon/widgets/icons/R.svg
orangecontrib/finecon/widgets/icons/category.svg
orangecontrib/finecon/widgets/icons/finecon.svg
